Metadata-Version: 2.1
Name: web-installation-instruction
Version: 0.5.1
Summary: Tool rendering html page from install.cfg file.
Author: Kanushka Gupta
Author-email: Adam McKellar <dev@mckellar.eu>, Timo Ege <timoege@online.de>
Maintainer: Kanushka Gupta
Maintainer-email: Adam McKellar <dev@mckellar.eu>, Timo Ege <timoege@online.de>
License: Apache-2.0
Project-URL: Repository, https://github.com/instructions-d-installation/web-installation-instruction
Project-URL: Issues, https://github.com/instructions-d-installation/web-installation-instruction/issues
Project-URL: Changelog, https://github.com/instructions-d-installation/web-installation-instruction/blob/main/CHANGELOG.md
Classifier: Programming Language :: Python :: 3
Classifier: Operating System :: OS Independent
Classifier: License :: OSI Approved :: Apache Software License
Requires-Python: >=3.10
License-File: LICENSE
Requires-Dist: jinja2
Requires-Dist: typer
Requires-Dist: installation-instruction>=0.4.0
